two_comp/__init__.py
two_comp-0.0.1.dist-info/LICENSE
two_comp-0.0.1.dist-info/METADATA
two_comp-0.0.1.dist-info/WHEEL
two_comp-0.0.1.dist-info/top_level.txt
two_comp-0.0.1.dist-info/RECORD
