Metadata-Version: 2.1
Name: two_comp
Version: 0.0.1
Author: james_tate
License: MIT License
Project-URL: Homepage, https://github.com/james-tate/two_comp
Project-URL: Repository, https://github.com/james-tate/two_comp
Requires-Python: >=3.8
License-File: LICENSE
Provides-Extra: develop
Requires-Dist: isort ; extra == 'develop'
Requires-Dist: black ; extra == 'develop'
Requires-Dist: pylint ; extra == 'develop'
Requires-Dist: pre-commit-hooks ; extra == 'develop'
Requires-Dist: pytest ; extra == 'develop'
Requires-Dist: random ; extra == 'develop'
Requires-Dist: ctypes ; extra == 'develop'
